<XnaContent>
  <Asset Type="SpaceCardGameData.ShipData">
    <TextureAsset>Cards\Stations\RaiuT'Ek\RaiuT'Ek</TextureAsset>
    <Attack>0</Attack>
    <Defence>15</Defence>
    <Speed>0</Speed>
    <TurretHardpoints>
      <Item>
        <X>0</X>
        <Y>-8</Y>
      </Item>
    </TurretHardpoints>
    <EngineHardpoints>
      <Item>
        <X>0</X>
        <Y>22</Y>
      </Item>
    </EngineHardpoints>
    <DamageHardpoints/>
    <ExplosionSFXAsset>Explosions\LargeShipDeathExplosion</ExplosionSFXAsset>
  </Asset>
</XnaContent>